README.rst
setup.py
time_complexity_estimator/__init__.py
time_complexity_estimator/complexities.py
time_complexity_estimator/complexity_fitter.py
time_complexity_estimator/estimator.py
time_complexity_estimator/logging_decorant.py
time_complexity_estimator/time_measurer.py
time_complexity_estimator.egg-info/.DS_Store
time_complexity_estimator.egg-info/PKG-INFO
time_complexity_estimator.egg-info/SOURCES.txt
time_complexity_estimator.egg-info/dependency_links.txt
time_complexity_estimator.egg-info/not-zip-safe
time_complexity_estimator.egg-info/requires.txt
time_complexity_estimator.egg-info/top_level.txt
time_complexity_estimator.egg-info/.git/.DS_Store
time_complexity_estimator.egg-info/.git/HEAD
time_complexity_estimator.egg-info/.git/config
time_complexity_estimator.egg-info/.git/description
time_complexity_estimator.egg-info/.git/index
time_complexity_estimator.egg-info/.git/sourcetreeconfig
time_complexity_estimator.egg-info/.git/hooks/applypatch-msg.sample
time_complexity_estimator.egg-info/.git/hooks/commit-msg.sample
time_complexity_estimator.egg-info/.git/hooks/post-update.sample
time_complexity_estimator.egg-info/.git/hooks/pre-applypatch.sample
time_complexity_estimator.egg-info/.git/hooks/pre-commit.sample
time_complexity_estimator.egg-info/.git/hooks/pre-push.sample
time_complexity_estimator.egg-info/.git/hooks/pre-rebase.sample
time_complexity_estimator.egg-info/.git/hooks/pre-receive.sample
time_complexity_estimator.egg-info/.git/hooks/prepare-commit-msg.sample
time_complexity_estimator.egg-info/.git/hooks/update.sample
time_complexity_estimator.egg-info/.git/info/exclude
time_complexity_estimator.egg-info/.git/objects/8b/137891791fe96927ad78e64b0aad7bded08bdc
time_complexity_estimator.egg-info/.git/objects/8c/d52d627a869ed4d15f3f7089f71b39156e6e9a
time_complexity_estimator.egg-info/.git/objects/ef/eb6e59f14265b9ba0a17d3198c5928061a7f8f
time_complexity_estimator.egg-info/.git/objects/f6/a7d35629e50667a479a331ec824bb0b7a41ac3