Metadata-Version: 1.0
Name: time-complexity-estimator
Version: 0.3
Summary: Estimate time complexity from execution time
Home-page: https://github.com/
Author: Mieszko Makuch
Author-email: mmakuch@googlemail.com
License: LICENSE.txt
Platform: UNKNOWN
